qctools/__init__.py
qctools/atominfo.py
qctools/cli.py
qctools/decorators.py
qctools/eventhandler.py
qctools/events.py
qctools/exceptions.py
qctools/fileinput.py
qctools/fileio.py
qctools/functions.py
qctools/gaussian_config.py
qctools/generator.py
qctools/molden_config.py
qctools/parser.py
qctools/qctools.py
qctools/utils.py
qctools/converter/__init__.py
qctools/converter/config_converters.py
qctools/converter/container.py
qctools/converter/converter.py
qctools/expression/__init__.py
qctools/expression/mathexpression.py
qctools/expression/pp_grammar.py
qctools/expression/pp_parser.py
qctools-0.2.0.dist-info/AUTHORS.rst
qctools-0.2.0.dist-info/LICENSE
qctools-0.2.0.dist-info/METADATA
qctools-0.2.0.dist-info/WHEEL
qctools-0.2.0.dist-info/top_level.txt
qctools-0.2.0.dist-info/RECORD
