Metadata-Version: 2.1
Name: qctools
Version: 0.2.0
Summary: Python tools for quantum chemists
Home-page: https://github.com/mfsjmenger/qctools
Author: Maximilian F.S.J. Menger
Author-email: m.f.s.j.menger@rug.nl
License: Apache License v2.0
Keywords: qctools
Platform: UNKNOWN
Classifier: Development Status :: 2 - Pre-Alpha
Classifier: Intended Audience :: Developers
Classifier: Natural Language :: English
Classifier: License :: OSI Approved :: Apache Software License
Classifier: Programming Language :: Python :: 3.5
Classifier: Programming Language :: Python :: 3.6
Classifier: Programming Language :: Python :: 3.7
Requires-Python: >=2.7, !=3.0.*, !=3.1.*, !=3.2.*, !=3.3.*, !=3.4.*
Requires-Dist: Click (>=6.0)
Requires-Dist: pycolt (>=0.2)
